infiniaml_idp_client/__init__.py
infiniaml_idp_client/_http_client_mixin.py
infiniaml_idp_client/credentials.py
infiniaml_idp_client/idp_client.py
infiniaml_idp_client/job_client.py
infiniaml_idp_client/paginator.py
infiniaml_idp_client/schemas.py
infiniaml_idp_client/_cli/__init__.py
infiniaml_idp_client/_cli/main.py
infiniaml_idp_client/_cli/project_models.py
infiniaml_idp_client/_cli/typed_dict_code_gen.py
infiniaml_idp_client/_cli/utils.py
infiniaml_idp_client/_common/constants.py
infiniaml_idp_client/_common/token.py
infiniaml_idp_client/_common/types.py
infiniaml_idp_client/aio/__init__.py
infiniaml_idp_client/aio/_http_client_mixin.py
infiniaml_idp_client/aio/credentials.py
infiniaml_idp_client/aio/idp_client.py
infiniaml_idp_client/aio/job_client.py
infiniaml_idp_client/aio/paginator.py
scripts/unasync-files.py
tests/__init__.py
tests/conftest.py
tests/generated_models.py
tests/async/__init__.py
tests/async/test_http_client_mixin.py
tests/async/test_job_client.py
tests/cli/__init__.py
tests/cli/test_create_project_models.py
tests/data/models_1.py
tests/data/models_2.py
tests/sync/__init__.py
tests/sync/test_http_client_mixin.py
tests/sync/test_job_client.py
infiniaml_idp_client-1.0.1.dist-info/METADATA
infiniaml_idp_client-1.0.1.dist-info/WHEEL
infiniaml_idp_client-1.0.1.dist-info/entry_points.txt
infiniaml_idp_client-1.0.1.dist-info/top_level.txt
infiniaml_idp_client-1.0.1.dist-info/RECORD
